pypass/__init__.py
pypass/command.py
pypass/entry_type.py
pypass/passwordstore.py
pypass/tests/__init__.py
pypass/tests/test_command.py
pypass/tests/test_key_sec.asc
pypass/tests/test_ownertrust.txt
pypass/tests/test_passwordstore.py
pypass-0.2.1.dist-info/DESCRIPTION.rst
pypass-0.2.1.dist-info/METADATA
pypass-0.2.1.dist-info/RECORD
pypass-0.2.1.dist-info/WHEEL
pypass-0.2.1.dist-info/entry_points.txt
pypass-0.2.1.dist-info/metadata.json
pypass-0.2.1.dist-info/pbr.json
pypass-0.2.1.dist-info/top_level.txt
