Metadata-Version: 2.0
Name: pypass
Version: 0.2.1
Summary: Pass in python
Home-page: https://github.com/ReAzem/python-pass
Author: Alexandre Viau
Author-email: alexandre@alexandreviau.net
License: UNKNOWN
Platform: UNKNOWN
Requires-Dist: click
Requires-Dist: colorama
Requires-Dist: enum34
Requires-Dist: pexpect
